conslyric/__init__.py
conslyric/exceptions.py
conslyric/interpreter.py
conslyric/parser.py
conslyric/std/__init__.py
conslyric/std/clear.py
conslyric/std/color_reset.py
conslyric/std/effect_reset.py
conslyric/std/enditer.py
conslyric/std/flash.py
conslyric/std/inplace.py
conslyric/std/iter.py
conslyric/std/noinplace.py
conslyric/std/setcolor.py
conslyric/std/seteffect_glitch.py
conslyric/std/seteffect_typewriter.py
conslyric-0.2.0.dist-info/WHEEL
conslyric-0.2.0.dist-info/entry_points.txt
conslyric-0.2.0.dist-info/METADATA
conslyric-0.2.0.dist-info/RECORD
