Metadata-Version: 2.3
Name: conslyric
Version: 0.2.0
Summary: Pythonで記述されたConslyric Schemaの実行環境
Author: AmaseCocoa
Author-email: AmaseCocoa <cocoa@amase.cc>
Requires-Dist: pyyaml>=6.0.3
Requires-Dist: typer>=0.20.0
Requires-Python: >=3.12
Project-URL: Issues, https://github.com/AmaseCocoa/conslyric/issues
Project-URL: Repository, https://github.com/AmaseCocoa/conslyric
